upapp/__init__.py
upapp/upapp.py
upapp-1.0.0.dist-info/METADATA
upapp-1.0.0.dist-info/WHEEL
upapp-1.0.0.dist-info/top_level.txt
upapp-1.0.0.dist-info/RECORD
