Metadata-Version: 2.1
Name: upapp
Version: 1.0.0
Summary: This is UPapp
Home-page: https://github.com/pro1mantis/UPapp
Author: Julij Dominik Mrak
Author-email: julij.dominik@yahoo.com
License: UNKNOWN
Project-URL: Issues, https://github.com/pro1mantis/UPapp/issues
Platform: UNKNOWN
Classifier: Programming Language :: Python :: 3
Classifier: License :: OSI Approved :: MIT License
Classifier: Operating System :: OS Independent
Requires-Python: >=3.6
